pyfuncol/__init__.py
pyfuncol/dict.py
pyfuncol/extend_builtins.py
pyfuncol/list.py
pyfuncol/set.py
pyfuncol-1.3.1.dist-info/LICENSE
pyfuncol-1.3.1.dist-info/METADATA
pyfuncol-1.3.1.dist-info/WHEEL
pyfuncol-1.3.1.dist-info/top_level.txt
pyfuncol-1.3.1.dist-info/RECORD
