Metadata-Version: 2.1
Name: pyfuncol
Version: 1.3.1
Summary: Functional collections extension functions for Python
Home-page: https://github.com/didactic-meme/pyfuncol
Author: Andrea Veneziano
Author-email: andrea.veneziano@icloud.com
Maintainer: Andrea Veneziano
Maintainer-email: andrea.veneziano@icloud.com
License: MIT
Keywords: functional pipeline data collection chain parallel
Platform: UNKNOWN
Classifier: Development Status :: 4 - Beta
Classifier: Intended Audience :: Developers
Classifier: License :: OSI Approved :: MIT License
Classifier: Programming Language :: Python :: 3.6
Classifier: Programming Language :: Python :: 3.7
Classifier: Programming Language :: Python :: 3.8
Classifier: Programming Language :: Python :: 3.9
Classifier: Programming Language :: Python :: Implementation :: CPython
Classifier: Natural Language :: English
Classifier: Operating System :: OS Independent
Classifier: Topic :: Software Development :: Libraries :: Python Modules
License-File: LICENSE
Requires-Dist: forbiddenfruit
Requires-Dist: dask
